README
README.md
setup.py
itermplot/__init__.py
itermplot.egg-info/PKG-INFO
itermplot.egg-info/SOURCES.txt
itermplot.egg-info/dependency_links.txt
itermplot.egg-info/not-zip-safe
itermplot.egg-info/requires.txt
itermplot.egg-info/top_level.txt