Metadata-Version: 1.0
Name: itermplot
Version: 0.321
Summary: An awesome iTerm2 backend for Matplotlib, so you can plot directly in your terminal.
Home-page: http://github.com/daleroberts/itermplot
Author: Dale Roberts
Author-email: dale.o.roberts@gmail.com
License: MIT
Platform: UNKNOWN
